opmentis/__init__.py
opmentis/core.py
opmentis/tests/__init__.py
opmentis/tests/pytest.ini
opmentis/tests/test_core.py
opmentis-0.2.4.1.dist-info/METADATA
opmentis-0.2.4.1.dist-info/WHEEL
opmentis-0.2.4.1.dist-info/RECORD
