Metadata-Version: 2.3
Name: opmentis
Version: 0.2.4.1
Summary: Library to register opmentis miners and check data and start new chat and many more
Home-page: https://github.com/OpMentis-Ai
License: MIT
Keywords: opmentis,miners,chat,data-analysis,ai
Author: opmentis
Author-email: admin@opmentis.xyz
Requires-Python: >=3.8.1
Classifier: License :: OSI Approved :: MIT License
Classifier: Programming Language :: Python :: 3
Classifier: Programming Language :: Python :: 3.9
Classifier: Programming Language :: Python :: 3.10
Classifier: Programming Language :: Python :: 3.11
Classifier: Programming Language :: Python :: 3.12
Classifier: Programming Language :: Python :: 3.13
Requires-Dist: requests (>=2.32.3,<3.0.0)
Requires-Dist: rich (>=13.9.4,<14.0.0)
Requires-Dist: tabulate (>=0.9.0)
Project-URL: Documentation, https://github.com/OpMentis-Ai/wiki
Project-URL: Repository, https://github.com/OpMentis-Ai
